cioc4d/Conductor.pyp
cioc4d/VERSION
cioc4d/__init__.py
cioc4d/asset_cache.py
cioc4d/conductor_dialog.py
cioc4d/conductor_store.py
cioc4d/const.py
cioc4d/foot_grp.py
cioc4d/head_grp.py
cioc4d/submit.py
cioc4d/utils.py
cioc4d/validation.py
cioc4d/res/c4d_symbols.h
cioc4d/res/conductorRender_30x30.png
cioc4d/res/dialogs/CONDUCTOR_DIALOG.res
cioc4d/res/strings_us/c4d_strings.str
cioc4d/res/strings_us/dialogs/CONDUCTOR_DIALOG.str
cioc4d/sections/__init__.py
cioc4d/sections/assets_section.py
cioc4d/sections/collapsible_section.py
cioc4d/sections/diagnostics_section.py
cioc4d/sections/environment_section.py
cioc4d/sections/frames_section.py
cioc4d/sections/general_section.py
cioc4d/sections/info_section.py
cioc4d/sections/location_section.py
cioc4d/sections/metadata_section.py
cioc4d/sections/notification_section.py
cioc4d/sections/preview_section.py
cioc4d/sections/retries_section.py
cioc4d/sections/software_section.py
cioc4d/sections/task_section.py
cioc4d/sections/upload_options_section.py
cioc4d/widgets/__init__.py
cioc4d/widgets/button_row.py
cioc4d/widgets/checkbox_grp.py
cioc4d/widgets/combo_box_grp.py
cioc4d/widgets/dual_combo_box_grp.py
cioc4d/widgets/hidable_text_field_grp.py
cioc4d/widgets/int_field_grp.py
cioc4d/widgets/key_value_widget.py
cioc4d/widgets/path_widget.py
cioc4d/widgets/text_area_grp.py
cioc4d/widgets/text_field_grp.py
cioc4d/widgets/text_grp.py
cioc4d/widgets/utils.py
cioc4d-1.1.1.dist-info/METADATA
cioc4d-1.1.1.dist-info/WHEEL
cioc4d-1.1.1.dist-info/top_level.txt
cioc4d-1.1.1.dist-info/RECORD
