Metadata-Version: 2.4
Name: cioc4d
Version: 1.1.1
Summary: C4D plugin for Conductor Cloud Rendering Platform.
Home-page: https://github.com/ConductorTechnologies/cioc4d
Author: conductor
Author-email: info@conductortech.com
Classifier: Operating System :: OS Independent
Classifier: Programming Language :: Python
Classifier: Topic :: Multimedia :: Graphics :: 3D Rendering
Requires-Dist: certifi==2019.11.28
Requires-Dist: ciocore<10.0.0,>=9.0.0
Requires-Dist: ciopath<2.0.0,>=1.1.2
Requires-Dist: cioseq<1.0.0,>=0.5.1
Requires-Dist: ciotemplate<1.0.0,>=0.1.2
Dynamic: author
Dynamic: author-email
Dynamic: classifier
Dynamic: description
Dynamic: description-content-type
Dynamic: home-page
Dynamic: requires-dist
Dynamic: summary
